Metadata-Version: 2.1
Name: odoo-addon-project_duplicate_subtask
Version: 16.0.1.0.0.13
Summary: The module adds an action to duplicate tasks with the child subtasks
Home-page: https://github.com/OCA/project
Author: Forgeflow, Odoo Community Association (OCA)
Author-email: support@odoo-community.org
License: AGPL-3
Classifier: Programming Language :: Python
Classifier: Framework :: Odoo
Classifier: Framework :: Odoo :: 16.0
Classifier: License :: OSI Approved :: GNU Affero General Public License v3
Requires-Python: >=3.10
Requires-Dist: odoo<16.1dev,>=16.0a
